{
    "uuid": [
        {
            "value": "e210dd6d-99d3-4848-9ac7-bd0c9f1c448c"
        }
    ],
    "langcode": [
        {
            "value": "bg"
        }
    ],
    "type": [
        {
            "target_id": "info_block",
            "target_type": "paragraphs_type",
            "target_uuid": "d12208bc-1576-4bc5-94e2-ae0ad9edb4c8"
        }
    ],
    "status": [
        {
            "value": true
        }
    ],
    "created": [
        {
            "value": "2021-09-08T08:17:27+00:00",
            "format": "Y-m-d\\TH:i:sP"
        }
    ],
    "behavior_settings": [
        {
            "value": []
        }
    ],
    "default_langcode": [
        {
            "value": true
        }
    ],
    "revision_translation_affected": [],
    "field_info_item": [
        {
            "target_type": "taxonomy_term",
            "target_uuid": "2c3471ad-ac96-4db2-b78e-f532f12dd13d"
        },
        {
            "target_type": "taxonomy_term",
            "target_uuid": "dbc48719-0adf-49b3-a4f4-a529e2da7997"
        },
        {
            "target_type": "taxonomy_term",
            "target_uuid": "718cede5-8997-494c-b341-3648baa2625e"
        }
    ],
    "field_landing_page_title": [
        {
            "value": true
        }
    ],
    "field_paragraph_title": [
        {
            "value": "\u0417\u043d\u0430\u0435\u043c \u043a\u0430\u043a \u0441\u0435 \u0445\u0440\u0430\u043d\u0438\u043c",
            "format": "basic_html"
        }
    ],
    "field_theme_light": [
        {
            "value": true
        }
    ]
}